MANIFEST.in
README.md
setup.cfg
setup.py
circus_logstash/__init__.py
circus_logstash/circus_logstash.py
circus_logstash.egg-info/PKG-INFO
circus_logstash.egg-info/SOURCES.txt
circus_logstash.egg-info/dependency_links.txt
circus_logstash.egg-info/entry_points.txt
circus_logstash.egg-info/requires.txt
circus_logstash.egg-info/top_level.txt
circus_logstash.egg-info/zip-safe