Metadata-Version: 1.0
Name: circus-logstash
Version: 0.0.5
Summary: A Logstash shipper for Circus
Home-page: https://github.com/seatgeek/circus-logstash
Author: Philip Cristiano
Author-email: phil@seatgeek.com
License: BSD
Keywords: logstash circus
Platform: UNKNOWN
